{
  "schemaVersion": 1,
  "levels": [
    {
      "name": "Intro Steps",
      "theme": {
        "bg": "#F0F0F0",
        "platform": "#333333",
        "blob": "#696969"
      },
      "gravity": 0.65,
      "jumpV": -11.0,
      "camera": { "lerp": 0.12 },
      "world": { "w": 2400, "h": 480, "deathY": 560 },
      "start": { "x": 80, "y": 220, "r": 26 },
      "platforms": [
        { "x": 0, "y": 400, "w": 1720, "h": 36, "color": "#000000" },

        { "x": 120, "y": 340, "w": 120, "h": 12 },
        { "x": 300, "y": 290, "w": 90, "h": 12 },
        { "x": 440, "y": 230, "w": 130, "h": 12 },
        { "x": 520, "y": 340, "w": 90, "h": 12 },
        { "x": 570, "y": 150, "w": 30, "h": 12 },

        { "x": 760, "y": 350, "w": 110, "h": 12 },
        { "x": 930, "y": 310, "w": 110, "h": 12 },
        { "x": 1090, "y": 270, "w": 110, "h": 12 },

        { "x": 1400, "y": 330, "w": 140, "h": 12 }
      ]
    }
  ]
}
